FullSubtractor/FullSubtractor.v
module FullSubtrator(A, B, Bin, Diff, Bout);
    output Diff, Bout;
    input A, B, Bin;

    assign Bout = ((~A) && (B ^ Bin) ) || (B && Bin);
    assign Diff = A ^ B ^ Bin;
endmodule

FullSubtractor/FullSubtractor_tb.v
`timescale 1ns/1ns
`include "FullSubtractor.v"

module FullSubtractor_tb;

    reg A, B, Bin;
    wire Diff, Bout;

    FullSubtrator FS(A, B, Bin, Diff, Bout);

    initial
    begin
        
        $dumpfile("wave.vcd");
        $dumpvars(0, FullSubtractor_tb);
        A = 0; B = 0; Bin = 0; # 10;
        A = 0; B = 0; Bin = 1; # 10;
        A = 0; B = 1; Bin = 0; # 10;
        A = 0; B = 1; Bin = 1; # 10;
        A = 1; B = 0; Bin = 0; # 10;
        A = 1; B = 0; Bin = 1; # 10;
        A = 1; B = 1; Bin = 0; # 10;
        A = 1; B = 1; Bin = 1; # 10;

    end


endmodule

FullSubtractor/wave.vcd
$date
	Sat Sep 20 21:58:56 2025
$end
$version
	Icarus Verilog
$end
$timescale
	1ns
$end
$scope module FullSubtractor_tb $end
$var wire 1 ! Diff $end
$var wire 1 " Bout $end
$var reg 1 # A $end
$var reg 1 $ B $end
$var reg 1 % Bin $end
$scope module FS $end
$var wire 1 # A $end
$var wire 1 $ B $end
$var wire 1 % Bin $end
$var wire 1 " Bout $end
$var wire 1 ! Diff $end
$upscope $end
$upscope $end
$enddefinitions $end
$comment Show the parameter values. $end
$dumpall
$end
#0
$dumpvars
0%
0$
0#
0"
0!
$end
#10
1"
1!
1%
#20
0%
1$
#30
0!
1%
#40
0"
1!
0%
0$
1#
#50
0!
1%
#60
0%
1$
#70
1"
1!
1%
