Exam/8Bit8ChannelMux/8bit8channelmux.v
module mux8bit_8channel(
    in0,
    in1,
    in2,
    in3,
    in4,
    in5,
    in6,
    in7,
    sel,
    out
);

    input wire [7:0] in0, in1, in2, in3, in4, in5, in6, in7;
    output reg [7:0] out;
    input wire [2:0] sel;

    always @(*) begin
        case (sel)
            3'b000: out = in0;
            3'b001: out = in1;
            3'b010: out = in2;
            3'b011: out = in3;
            3'b100: out = in4;
            3'b101: out = in5;
            3'b110: out = in6;
            3'b111: out = in7;
        endcase
    end

endmodule

Exam/8Bit8ChannelMux/main.v
`timescale 1ns/1ns
`include "8bit8channelmux.v"

module mux8bit_8channel_tb;

    reg [7:0] in0, in1, in2, in3, in4, in5, in6, in7;
    wire [7:0] out;
    reg [2:0] sel;

    mux8bit_8channel mux (
        .in0(in0),
        .in1(in1),
        .in2(in2),
        .in3(in3),
        .in4(in4),
        .in5(in5),
        .in6(in6),
        .in7(in7),
        .sel(sel),
        .out(out)
    );

    initial begin
        $dumpfile("wave.vcd");
        $dumpvars(0, mux8bit_8channel_tb);
        // Initialize inputs
        in0 = 8'b00000001;
        in1 = 8'b00000010;
        in2 = 8'b00000100;
        in3 = 8'b00001000;
        in4 = 8'b00010000;
        in5 = 8'b00100000;
        in6 = 8'b01000000;
        in7 = 8'b10000000;

        // Test all select lines
        sel = 3'b000; #10;
        sel = 3'b001; #10;
        sel = 3'b010; #10;
        sel = 3'b011; #10;
        sel = 3'b100; #10;
        sel = 3'b101; #10;
        sel = 3'b110; #10;
        sel = 3'b111; #10;
    end

endmodule

Exam/8Bit8ChannelMux/wave.vcd
$date
	Tue Nov 18 18:15:09 2025
$end
$version
	Icarus Verilog
$end
$timescale
	1ns
$end
$scope module mux8bit_8channel_tb $end
$var wire 8 ! out [7:0] $end
$var reg 8 " in0 [7:0] $end
$var reg 8 # in1 [7:0] $end
$var reg 8 $ in2 [7:0] $end
$var reg 8 % in3 [7:0] $end
$var reg 8 & in4 [7:0] $end
$var reg 8 ' in5 [7:0] $end
$var reg 8 ( in6 [7:0] $end
$var reg 8 ) in7 [7:0] $end
$var reg 3 * sel [2:0] $end
$scope module mux $end
$var wire 8 + in0 [7:0] $end
$var wire 8 , in1 [7:0] $end
$var wire 8 - in2 [7:0] $end
$var wire 8 . in3 [7:0] $end
$var wire 8 / in4 [7:0] $end
$var wire 8 0 in5 [7:0] $end
$var wire 8 1 in6 [7:0] $end
$var wire 8 2 in7 [7:0] $end
$var wire 3 3 sel [2:0] $end
$var reg 8 4 out [7:0] $end
$upscope $end
$upscope $end
$enddefinitions $end
$comment Show the parameter values. $end
$dumpall
$end
#0
$dumpvars
b1 4
b0 3
b10000000 2
b1000000 1
b100000 0
b10000 /
b1000 .
b100 -
b10 ,
b1 +
b0 *
b10000000 )
b1000000 (
b100000 '
b10000 &
b1000 %
b100 $
b10 #
b1 "
b1 !
$end
#10
b10 !
b10 4
b1 *
b1 3
#20
b100 !
b100 4
b10 *
b10 3
#30
b1000 !
b1000 4
b11 *
b11 3
#40
b10000 !
b10000 4
b100 *
b100 3
#50
b100000 !
b100000 4
b101 *
b101 3
#60
b1000000 !
b1000000 4
b110 *
b110 3
#70
b10000000 !
b10000000 4
b111 *
b111 3
