Exam/8Bit8ChannelDeMux/8bit8channeldemux.v
module demux8bit_8channel(
    data_in,
    sel,
    out0,
    out1,
    out2,
    out3,
    out4,
    out5,
    out6,
    out7
);
    input wire [7:0] data_in;
    input wire [2:0] sel;
    output reg [7:0] out0, out1, out2, out3, out4, out5, out6, out7;

    always @(sel)
    begin
        case (sel)
            3'd0: begin
                // Reset registers
                out0 = 8'd0; out1 = 8'd0; out2 = 8'd0; out3 = 8'd0; out4 = 8'd0; out5 = 8'd0; out6 = 8'd0; out7 = 8'd0;
                out0 = data_in;
            end
            3'd1: begin
                out0 = 8'd0; out1 = 8'd0; out2 = 8'd0; out3 = 8'd0; out4 = 8'd0; out5 = 8'd0; out6 = 8'd0; out7 = 8'd0;
                out1 = data_in;
            end
            3'd2: begin
                out0 = 8'd0; out1 = 8'd0; out2 = 8'd0; out3 = 8'd0; out4 = 8'd0; out5 = 8'd0; out6 = 8'd0; out7 = 8'd0;
                out2 = data_in;
            end
            3'd3: begin
                out0 = 8'd0; out1 = 8'd0; out2 = 8'd0; out3 = 8'd0; out4 = 8'd0; out5 = 8'd0; out6 = 8'd0; out7 = 8'd0;
                out3 = data_in;
            end
            3'd4: begin
                out0 = 8'd0; out1 = 8'd0; out2 = 8'd0; out3 = 8'd0; out4 = 8'd0; out5 = 8'd0; out6 = 8'd0; out7 = 8'd0;
                out4 = data_in;
            end
            3'd5: begin
                out0 = 8'd0; out1 = 8'd0; out2 = 8'd0; out3 = 8'd0; out4 = 8'd0; out5 = 8'd0; out6 = 8'd0; out7 = 8'd0;
                out5 = data_in;
            end
            3'd6: begin
                out0 = 8'd0; out1 = 8'd0; out2 = 8'd0; out3 = 8'd0; out4 = 8'd0; out5 = 8'd0; out6 = 8'd0; out7 = 8'd0;
                out6 = data_in;
            end
            3'd7: begin
                out0 = 8'd0; out1 = 8'd0; out2 = 8'd0; out3 = 8'd0; out4 = 8'd0; out5 = 8'd0; out6 = 8'd0; out7 = 8'd0;
                out7 = data_in;
            end
        endcase
    end


endmodule

Exam/8Bit8ChannelDeMux/main.v
`timescale 1ns/1ns
`include "8bit8channeldemux.v"

module demux8bit_8channel_tb;

    reg [2:0] sel;
    reg [7:0] data_input;
    wire [7:0] out0, out1, out2, out3, out4, out5, out6, out7;

    demux8bit_8channel demux (
        .data_in(data_input),
        .sel(sel),
        .out0(out0),
        .out1(out1),
        .out2(out2),
        .out3(out3),
        .out4(out4),
        .out5(out5),
        .out6(out6),
        .out7(out7)
    );

    initial begin
        $dumpfile("wave.vcd");
        $dumpvars(0, demux8bit_8channel_tb);
        // Initialize inputs
        data_input = 8'b10101010;
        sel = 3'b000; #10;
        sel = 3'b001; #10;
        sel = 3'b010; #10;
        sel = 3'b011; #10;
        sel = 3'b100; #10;
        sel = 3'b101; #10;
        sel = 3'b110; #10;
        sel = 3'b111; #10;
    end


endmodule

Exam/8Bit8ChannelDeMux/wave.vcd
$date
	Tue Nov 18 18:16:34 2025
$end
$version
	Icarus Verilog
$end
$timescale
	1ns
$end
$scope module demux8bit_8channel_tb $end
$var wire 8 ! out7 [7:0] $end
$var wire 8 " out6 [7:0] $end
$var wire 8 # out5 [7:0] $end
$var wire 8 $ out4 [7:0] $end
$var wire 8 % out3 [7:0] $end
$var wire 8 & out2 [7:0] $end
$var wire 8 ' out1 [7:0] $end
$var wire 8 ( out0 [7:0] $end
$var reg 8 ) data_input [7:0] $end
$var reg 3 * sel [2:0] $end
$scope module demux $end
$var wire 8 + data_in [7:0] $end
$var wire 3 , sel [2:0] $end
$var reg 8 - out0 [7:0] $end
$var reg 8 . out1 [7:0] $end
$var reg 8 / out2 [7:0] $end
$var reg 8 0 out3 [7:0] $end
$var reg 8 1 out4 [7:0] $end
$var reg 8 2 out5 [7:0] $end
$var reg 8 3 out6 [7:0] $end
$var reg 8 4 out7 [7:0] $end
$upscope $end
$upscope $end
$enddefinitions $end
$comment Show the parameter values. $end
$dumpall
$end
#0
$dumpvars
b0 4
b0 3
b0 2
b0 1
b0 0
b0 /
b0 .
b10101010 -
b0 ,
b10101010 +
b0 *
b10101010 )
b10101010 (
b0 '
b0 &
b0 %
b0 $
b0 #
b0 "
b0 !
$end
#10
b10101010 '
b10101010 .
b0 (
b0 -
b1 *
b1 ,
#20
b10101010 &
b10101010 /
b0 '
b0 .
b10 *
b10 ,
#30
b10101010 %
b10101010 0
b0 &
b0 /
b11 *
b11 ,
#40
b10101010 $
b10101010 1
b0 %
b0 0
b100 *
b100 ,
#50
b10101010 #
b10101010 2
b0 $
b0 1
b101 *
b101 ,
#60
b10101010 "
b10101010 3
b0 #
b0 2
b110 *
b110 ,
#70
b10101010 !
b10101010 4
b0 "
b0 3
b111 *
b111 ,
