Mux2-1/mux2-1.v
module mux2(A, B, S, O);
    output O;
    input A, B, S;

    assign O = (A && S) || (B && ~S);

endmodule

Mux2-1/main.v
`timescale 1ns/1ns
`include "mux2-1.v"

module mux2_tb;

    reg A, B, S;
    wire O;

    mux2 MUX2(A, B, S, O);

    initial
    begin

        $dumpfile("wave.vcd");
        $dumpvars(0, mux2_tb);

        A = 0; B = 0; S = 0; #10;
        A = 0; B = 0; S = 1; #10;
        A = 0; B = 1; S = 0; #10;
        A = 0; B = 1; S = 1; #10;
        A = 1; B = 0; S = 0; #10;
        A = 1; B = 0; S = 1; #10;
        A = 1; B = 1; S = 0; #10;
        A = 1; B = 1; S = 1; #10;
        

        
        
    end

endmodule

Mux2-1/wave.vcd
$date
	Mon Sep 22 21:12:04 2025
$end
$version
	Icarus Verilog
$end
$timescale
	1ns
$end
$scope module mux2_tb $end
$var wire 1 ! O $end
$var reg 1 " A $end
$var reg 1 # B $end
$var reg 1 $ S $end
$scope module MUX2 $end
$var wire 1 " A $end
$var wire 1 # B $end
$var wire 1 ! O $end
$var wire 1 $ S $end
$upscope $end
$upscope $end
$enddefinitions $end
$comment Show the parameter values. $end
$dumpall
$end
#0
$dumpvars
0$
0#
0"
0!
$end
#10
1$
#20
1!
0$
1#
#30
0!
1$
#40
0$
0#
1"
#50
1!
1$
#60
0$
1#
#70
1$
