FullAdder-SOP/full_adder.v
module full_adder(A, B, Cin, Sum, Cout);
    output Sum, Cout;
    input A, B, Cin;

    assign Cout = (~A && B && Cin) || (A && ~B && Cin) || (A && B && ~Cin) || (A && B && Cin);
    assign Sum = (~A && ~B && Cin)  || (~A && B && ~Cin) || (A && ~B && ~Cin)  || (A && B && Cin);


endmodule

FullAdder-SOP/full_adder_tb.v
`timescale 1ns/1ns
`include "full_adder.v"

module full_adder_tb;

    reg A, B, Cin;
    wire Sum, Cout;

    full_adder FA(A, B, Cin, Sum, Cout);

    initial begin
        $dumpfile("full_adder_tb.vcd");
        $dumpvars(0, full_adder_tb);
        
        A = 0; B = 0; Cin = 0; #20;
        A = 0; B = 0; Cin = 1; #20;
        A = 0; B = 1; Cin = 0; #20;
        A = 0; B = 1; Cin = 1; #20;
        A = 1; B = 0; Cin = 0; #20;
        A = 1; B = 0; Cin = 1; #20;
        A = 1; B = 1; Cin = 0; #20;
        A = 1; B = 1; Cin = 1; #20;

    end
endmodule

FullAdder-SOP/full_adder_tb.vcd
$date
	Mon Sep 15 18:13:37 2025
$end
$version
	Icarus Verilog
$end
$timescale
	1ns
$end
$scope module full_adder_tb $end
$var wire 1 ! Sum $end
$var wire 1 " Cout $end
$var reg 1 # A $end
$var reg 1 $ B $end
$var reg 1 % Cin $end
$scope module FA $end
$var wire 1 # A $end
$var wire 1 $ B $end
$var wire 1 % Cin $end
$var wire 1 " Cout $end
$var wire 1 ! Sum $end
$upscope $end
$upscope $end
$enddefinitions $end
$comment Show the parameter values. $end
$dumpall
$end
#0
$dumpvars
0%
0$
0#
0"
0!
$end
#20
1!
1%
#40
0%
1$
#60
0!
1"
1%
#80
0"
1!
0%
0$
1#
#100
1"
0!
1%
#120
0%
1$
#140
1!
1%
